[{"id":"6282215393363@s.whatsapp.net","saldo":380255,"status":true,"deposit":"FS300525VR13626","reff_deposit":true,"tanggal_deposit":"","reff":"","level":"OWNER","toxiccount":"","responList":[{"respon":"120363311623867328@g.us","key":"allan","response":"🔰 Harga personal 1 PC 🖥 🔰\n♥ Point Blank Zepetto\n➡️ 1 Hari : Rp.10.000\n➡️ 2 Hari : Rp.15.000\n➡️ 3 Hari : Rp.20.000\n➡️ 5 Hari : Rp.25.000\n➡️ 13 Hari : Rp.50.000\n➡️ 19 Hari : Rp.70.000\n➡️ 27 Hari : Rp. 90.000\n➡️ 37 Hari : Rp.100.000\n➡️ 71 Hari : Rp.180.000\n➡️ 106 Hari : Rp.250.000","isImage":"🔰 Harga personal 1 PC 🖥 🔰\n♥ Point Blank Zepetto\n➡️ 1 Hari : Rp.10.000\n➡️ 2 Hari : Rp.15.000\n➡️ 3 Hari : Rp.20.000\n➡️ 5 Hari : Rp.25.000\n➡️ 13 Hari : Rp.50.000\n➡️ 19 Hari : Rp.70.000\n➡️ 27 Hari : Rp. 90.000\n➡️ 37 Hari : Rp.100.000\n➡️ 71 Hari : Rp.180.000\n➡️ 106 Hari : Rp.250.000","image_url":false}]},{"id":"120363311623867328@g.us","chats":{"120363311623867328@g.us":{"antilink":false,"antibot":false,"antibot2":false,"antilinktt":false,"antiaudio":false,"antisticker":false,"antiimage":false,"antivideo":false,"antidocument":false,"antitoxic":false,"antivirtex":false,"antipromosi":false,"antiwame":false,"antiwame2":false,"antipolling":false,"antilinkall":false,"antilink2":false,"autodl":false,"autoaigc":false,"autoaipc":false,"kickme":false,"keamanan":false,"mute":false,"antitagsw":false,"nsfw":false}},"sewa":{"mulai":1748506841510,"expired":1751098841510}},{"id":"6283116147347@s.whatsapp.net","saldo":0,"status":true,"deposit":"","reff_deposit":true,"tanggal_deposit":"","reff":"","level":"BRONZE","toxiccount":0},{"groupID":"6282215393363@s.whatsapp.net","responList":[]},{"groupID":"120363311623867328@g.us","responList":[]},{"id":"628989840009@s.whatsapp.net","saldo":0,"status":true,"deposit":"","reff_deposit":true,"tanggal_deposit":"","reff":"","level":"BRONZE","toxiccount":0},{"id":"6285936199757@s.whatsapp.net","saldo":0,"status":true,"deposit":"","reff_deposit":true,"tanggal_deposit":"","reff":"","level":"BRONZE","toxiccount":0},{"groupID":"6285936199757@s.whatsapp.net","responList":[]},{"id":"6281999617814@s.whatsapp.net","saldo":0,"status":true,"deposit":"","reff_deposit":true,"tanggal_deposit":"","reff":"","level":"BRONZE","toxiccount":0},{"id":"6289512745761@s.whatsapp.net","saldo":0,"status":true,"deposit":"","reff_deposit":true,"tanggal_deposit":"","reff":"","level":"BRONZE","toxiccount":0},{"groupID":"6289512745761@s.whatsapp.net","responList":[]},{"id":"6285156476017@s.whatsapp.net","premium":{"mulai":1748530120032,"expired":1751122120032}},{"groupID":"6285156476017@s.whatsapp.net","responList":[]},{"id":"6287777275723@s.whatsapp.net","saldo":0,"status":true,"deposit":"","reff_deposit":true,"tanggal_deposit":"","reff":"","level":"BRONZE","toxiccount":0}]